Workbook

Sheet Input and sensitivity
A1: Valuation drivers | D1: Sensitivity Analysis | F1: EBIT margin
A2: Base year for valuation | B2: 2024 | E2: ='Valuation output'!B29 -> #DIV/0! | F2: =G2-1% -> 0.4 | G2: =H2-1% -> 0.41 | H2: =I2-1% -> 0.42 | I2: =J2-1% -> 0.43 | J2: =K2-1% -> 0.44 | K2: 0.45 | L2: =K2+1% -> 0.46 | M2: =L2+1% -> 0.47 | N2: =M2+1% -> 0.48 | O2: =N2+1% -> 0.49 | P2: =O2+1% -> 0.5
A3: Revenue growth for forecast year 1 | D3: Revenue growth | E3: =E4-1% -> 0.03 | F3: #DIV/0! | G3: #DIV/0! | H3: #DIV/0! | I3: #DIV/0! | J3: #DIV/0! | K3: #DIV/0! | L3: #DIV/0! | M3: #DIV/0! | N3: #DIV/0! | O3: #DIV/0! | P3: #DIV/0!
A4: Compound annual revenue growth rate for forecast year 2-5 | E4: =E5-1% -> 0.04 | F4: #DIV/0! | G4: #DIV/0! | H4: #DIV/0! | I4: #DIV/0! | J4: #DIV/0! | K4: #DIV/0! | L4: #DIV/0! | M4: #DIV/0! | N4: #DIV/0! | O4: #DIV/0! | P4: #DIV/0!
A5: Revenue growth for terminal year (equal to risk-free rate) | E5: =E6-1% -> 0.05 | F5: #DIV/0! | G5: #DIV/0! | H5: #DIV/0! | I5: #DIV/0! | J5: #DIV/0! | K5: #DIV/0! | L5: #DIV/0! | M5: #DIV/0! | N5: #DIV/0! | O5: #DIV/0! | P5: #DIV/0!
A6: Target EBIT margin for long term | E6: =E7-1% -> 0.06 | F6: #DIV/0! | G6: #DIV/0! | H6: #DIV/0! | I6: #DIV/0! | J6: #DIV/0! | K6: #DIV/0! | L6: #DIV/0! | M6: #DIV/0! | N6: #DIV/0! | O6: #DIV/0! | P6: #DIV/0!
A7: Years to reach target EBIT margin | E7: =E8-1% -> 0.07 | F7: #DIV/0! | G7: #DIV/0! | H7: #DIV/0! | I7: #DIV/0! | J7: #DIV/0! | K7: #DIV/0! | L7: #DIV/0! | M7: #DIV/0! | N7: #DIV/0! | O7: #DIV/0! | P7: #DIV/0!
A8: Revenue to capital ratio (next 2 years) | E8: 0.08 | F8: #DIV/0! | G8: #DIV/0! | H8: #DIV/0! | I8: #DIV/0! | J8: #DIV/0! | K8: #DIV/0! | L8: #DIV/0! | M8: #DIV/0! | N8: #DIV/0! | O8: #DIV/0! | P8: #DIV/0!
A9: Revenue to capital ratio (FY3-5) | E9: =E8+1% -> 0.09 | F9: #DIV/0! | G9: #DIV/0! | H9: #DIV/0! | I9: #DIV/0! | J9: #DIV/0! | K9: #DIV/0! | L9: #DIV/0! | M9: #DIV/0! | N9: #DIV/0! | O9: #DIV/0! | P9: #DIV/0!
A10: Revenue to capital ratio (FY5-10) | E10: =E9+1% -> 0.1 | F10: #DIV/0! | G10: #DIV/0! | H10: #DIV/0! | I10: #DIV/0! | J10: #DIV/0! | K10: #DIV/0! | L10: #DIV/0! | M10: #DIV/0! | N10: #DIV/0! | O10: #DIV/0! | P10: #DIV/0!
A11: WACC for forecast year 1-5 | E11: =E10+1% -> 0.11 | F11: #DIV/0! | G11: #DIV/0! | H11: #DIV/0! | I11: #DIV/0! | J11: #DIV/0! | K11: #DIV/0! | L11: #DIV/0! | M11: #DIV/0! | N11: #DIV/0! | O11: #DIV/0! | P11: #DIV/0!
A12: Terminal WACC | E12: =E11+1% -> 0.12 | F12: #DIV/0! | G12: #DIV/0! | H12: #DIV/0! | I12: #DIV/0! | J12: #DIV/0! | K12: #DIV/0! | L12: #DIV/0! | M12: #DIV/0! | N12: #DIV/0! | O12: #DIV/0! | P12: #DIV/0!
A13: Return on new invested capital for the long term | E13: =E12+1% -> 0.13 | F13: #DIV/0! | G13: #DIV/0! | H13: #DIV/0! | I13: #DIV/0! | J13: #DIV/0! | K13: #DIV/0! | L13: #DIV/0! | M13: #DIV/0! | N13: #DIV/0! | O13: #DIV/0! | P13: #DIV/0!
A14: Effective tax rate
A16: WACC parameters
A17: Risk free rate
A18: Cost of debt
A19: Total equity risk premium
A20: Beta

Sheet Valuation output
A1: [Company Name] | B1: Base year | C1: 1 | D1: 2 | E1: 3 | F1: 4 | G1: 5 | H1: 6 | I1: 7 | J1: 8 | K1: 9 | L1: 10 | M1: Terminal year
A2: Year | B2: ='Input and sensitivity'!B2 -> 2024 | C2: =B2+1 -> 2025 | D2: =C2+1 -> 2026 | E2: =D2+1 -> 2027 | F2: =E2+1 -> 2028 | G2: =F2+1 -> 2029 | H2: =G2+1 -> 2030 | I2: =H2+1 -> 2031 | J2: =I2+1 -> 2032 | ... L2: =K2+1 -> 2034
A3: Revenue growth rate | C3: ='Input and sensitivity'!B3 -> 0 | D3: ='Input and sensitivity'!B4 -> 0 | E3: =D3 -> 0 | F3: =E3 -> 0 | G3: =F3 -> 0 | H3: =G3-($G$3-$M$3)/5 -> 0 | I3: =H3-($G$3-$M$3)/5 -> 0 | J3: =I3-($G$3-$M$3)/5 -> 0 | K3: =J3-($G$3-$M$3)/5 -> 0 | L3: =K3-($G$3-$M$3)/5 -> 0 | M3: ='Input and sensitivity'!B5 -> 0
A4: Revenue | C4: =B4*(1+C3) -> 0 | D4: =C4*(1+D3) -> 0 | E4: =D4*(1+E3) -> 0 | F4: =E4*(1+F3) -> 0 | G4: =F4*(1+G3) -> 0 | H4: =G4*(1+H3) -> 0 | I4: =H4*(1+I3) -> 0 | J4: =I4*(1+J3) -> 0 | ... M4: =L4*(1+M3) -> 0
A5: Operating Profit (EBIT) margin | B5: =B6/B4 -> #DIV/0! | C5: =IF(C1>$B$35,$M$5,$M$5-(($M$5-$B$5)/$B$35)*($B$35-C1)) -> 0 | D5: =IF(D1>$B$35,$M$5,$M$5-(($M$5-$B$5)/$B$35)*($B$35-D1)) -> 0 | E5: =IF(E1>$B$35,$M$5,$M$5-(($M$5-$B$5)/$B$35)*($B$35-E1)) -> 0 | F5: =IF(F1>$B$35,$M$5,$M$5-(($M$5-$B$5)/$B$35)*($B$35-F1)) -> 0 | G5: =IF(G1>$B$35,$M$5,$M$5-(($M$5-$B$5)/$B$35)*($B$35-G1)) -> 0 | H5: =IF(H1>$B$35,$M$5,$M$5-(($M$5-$B$5)/$B$35)*($B$35-H1)) -> 0 | I5: =IF(I1>$B$35,$M$5,$M$5-(($M$5-$B$5)/$B$35)*($B$35-I1)) -> 0 | J5: =IF(J1>$B$35,$M$5,$M$5-(($M$5-$B$5)/$B$35)*($B$35-J1)) -> 0 | ... L5: =IF(L1>$B$35,$M$5,$M$5-(($M$5-$B$5)/$B$35)*($B$35-L1)) -> 0 | M5: ='Input and sensitivity'!B6 -> 0
A6: Operating Profit (EBIT) | C6: =C5*C4 -> 0 | D6: =D5*D4 -> 0 | E6: =E5*E4 -> 0 | F6: =F5*F4 -> 0 | G6: =G5*G4 -> 0 | H6: =H5*H4 -> 0 | I6: =I5*I4 -> 0 | J6: =J5*J4 -> 0 | ... M6: =M5*M4 -> 0
A7: Tax to EBIT | B7: ='Input and sensitivity'!B14 -> 0 | C7: =$B$7 -> 0 | D7: =$B$7 -> 0 | E7: =$B$7 -> 0 | F7: =$B$7 -> 0 | G7: =$B$7 -> 0 | H7: =$B$7 -> 0 | I7: =$B$7 -> 0 | J7: =$B$7 -> 0 | ... M7: =$B$7 -> 0
A8: EBIT(1-t) | B8: =B6*(1-B7) -> 0 | C8: =C6*(1-C7) -> 0 | D8: =D6*(1-D7) -> 0 | E8: =E6*(1-E7) -> 0 | F8: =F6*(1-F7) -> 0 | G8: =G6*(1-G7) -> 0 | H8: =H6*(1-H7) -> 0 | I8: =I6*(1-I7) -> 0 | ... M8: =M6*(1-M7) -> 0
A9: - Reinvestment | C9: =IF(C32=0,0,IF(C4>B4,(C4-B4)/C32,0)) -> 0 | D9: =IF(D32=0,0,(D4-C4)/D32) -> 0 | E9: =IF(E32=0,0,(E4-D4)/E32) -> 0 | F9: =IF(F32=0,0,(F4-E4)/F32) -> 0 | G9: =IF(G32=0,0,(G4-F4)/G32) -> 0 | H9: =IF(H32=0,0,(H4-G4)/H32) -> 0 | I9: =IF(I32=0,0,(I4-H4)/I32) -> 0 | J9: =IF(J32=0,0,(J4-I4)/J32) -> 0 | K9: =IF(K32=0,0,(K4-J4)/K32) -> 0 | L9: =IF(L32=0,0,(L4-K4)/L32) -> 0 | M9: =IF(M3>0,(M3/M34)*M8,0) -> 0
A10: Free cash flow (FCFF) | B10: =B8-B9 -> 0 | C10: =C8-C9 -> 0 | D10: =D8-D9 -> 0 | E10: =E8-E9 -> 0 | F10: =F8-F9 -> 0 | G10: =G8-G9 -> 0 | H10: =H8-H9 -> 0 | I10: =I8-I9 -> 0 | ... M10: =M8-M9 -> 0
A12: WACC | B12: ='Input and sensitivity'!B11 -> 0 | C12: =B12 -> 0 | D12: =C12 -> 0 | E12: =D12 -> 0 | F12: =E12 -> 0 | G12: =F12 -> 0 | H12: =G12-($G$12-$M$12)/5 -> 0 | I12: =H12-($G$12-$M$12)/5 -> 0 | J12: =I12-($G$12-$M$12)/5 -> 0 | K12: =J12-($G$12-$M$12)/5 -> 0 | L12: =K12-($G$12-$M$12)/5 -> 0 | M12: ='Input and sensitivity'!B12 -> 0
A13: Discount factor | C13: =1/(1+C12)^1 -> 1 | D13: =1/(1+D12)^2 -> 1 | E13: =1/(1+E12)^3 -> 1 | F13: =1/(1+F12)^4 -> 1 | G13: =1/(1+G12)^5 -> 1 | H13: =1/(1+H12)^6 -> 1 | I13: =1/(1+I12)^7 -> 1 | J13: =1/(1+J12)^8 -> 1 | K13: =1/(1+K12)^9 -> 1 | L13: =1/(1+L12)^10 -> 1
A14: PV (Forecast period) | C14: =C13*C10 -> 0 | D14: =D13*D10 -> 0 | E14: =E13*E10 -> 0 | F14: =F13*F10 -> 0 | G14: =G13*G10 -> 0 | H14: =H13*H10 -> 0 | I14: =I13*I10 -> 0 | J14: =J13*J10 -> 0 | ... M14: =M13*M10 -> 0
A16: Terminal cash flow | B16: =M10 -> 0
A17: Terminal WACC | B17: =M12 -> 0
A18: Terminal value | B18: =B16/(B17-M3) -> #DIV/0!
A19: PV (Terminal value) | B19: =B18*L13 -> #DIV/0! | C19: =B19/B21 -> #DIV/0!
A20: PV (CF over next 10 years) | B20: =SUM(C14:L14) -> 0 | C20: =B20/B21 -> #DIV/0!
A21: PV total | B21: =B20+B19 -> #DIV/0!
A22: + Cash
A23: + Investments
A24: Enterprise value | B24: =B21+B22+B23 -> #DIV/0!
A25: - Debt
A26: - Minority
A27: Equity value | B27: =B24-B25-B26 -> #DIV/0!
A28: / Number of shares
A29: Price per share | B29: =B27/B28*1000000 -> #DIV/0!
A31: Implied variables
A32: Revenue to capital ratio | B32: =B4/B33 -> #DIV/0! | C32: ='Input and sensitivity'!B8 -> 0 | D32: =C32 -> 0 | E32: ='Input and sensitivity'!B9 -> 0 | F32: =E32 -> 0 | G32: =F32 -> 0 | H32: ='Input and sensitivity'!B10 -> 0 | I32: =H32 -> 0 | J32: =I32 -> 0 | K32: =J32 -> 0 | L32: =K32 -> 0
A33: Invested capital | C33: =B33+C9 -> 0 | D33: =C33+D9 -> 0 | E33: =D33+E9 -> 0 | F33: =E33+F9 -> 0 | G33: =F33+G9 -> 0 | H33: =G33+H9 -> 0 | I33: =H33+I9 -> 0 | J33: =I33+J9 -> 0 | ... L33: =K33+L9 -> 0
A34: ROIC | B34: =B8/B33 -> #DIV/0! | C34: =C8/C33 -> #DIV/0! | D34: =D8/D33 -> #DIV/0! | E34: =E8/E33 -> #DIV/0! | F34: =F8/F33 -> #DIV/0! | G34: =G8/G33 -> #DIV/0! | H34: =H8/H33 -> #DIV/0! | I34: =I8/I33 -> #DIV/0! | ... L34: =L8/L33 -> #DIV/0! | M34: ='Input and sensitivity'!B13 -> 0
A35: Years of convergence -EBIT margin | B35: ='Input and sensitivity'!B7 -> 0
